Metadata-Version: 2.1
Name: poetry-ryabov1
Version: 1.0.0
Summary: dangerous
Home-page: UNKNOWN
Author: NuatStanskiy
Author-email: smiril13@mail.ru
License: Apache License, Version 2.0, see LICENSE file
Platform: UNKNOWN
